tracker/__init__.py
tracker/app.py
CryptoTracker-0.1.2.dist-info/LICENSE
CryptoTracker-0.1.2.dist-info/METADATA
CryptoTracker-0.1.2.dist-info/WHEEL
CryptoTracker-0.1.2.dist-info/top_level.txt
CryptoTracker-0.1.2.dist-info/RECORD
