Metadata-Version: 2.1
Name: CryptoTracker
Version: 0.1.2
Summary: A simple GUI application to track cryptocurrency projects.
Home-page: https://github.com/DanFrolov
Download-URL: https://github.com/DanFrolov/crypto_tracker/archive/refs/tags/v01.1.1.zip
Author: DanF
License: MIT
Classifier: Development Status :: 3 - Alpha
Classifier: Intended Audience :: Developers
Classifier: Topic :: Software Development :: Build Tools
Classifier: License :: OSI Approved :: MIT License
Classifier: Programming Language :: Python :: 3
Classifier: Programming Language :: Python :: 3.7
Classifier: Programming Language :: Python :: 3.8
Classifier: Programming Language :: Python :: 3.9
Classifier: Programming Language :: Python :: 3.10
Requires-Python: >=3.7
License-File: LICENSE
Requires-Dist: pandas
